{
  "last_session": "20260401-020000",
  "best_score": 10.00,
  "total_sessions": 50,
  "policy_name": "beta",
  "season": "beta-teams-tiny-fixed",
  "tournament_best": 10.00,
  "tournament_rank": 1,
  "tournament_top": 10.00,
  "freeplay_best": 1.81,
  "freeplay_season": "beta-cvc",
  "latest_submission": "beta:v81",
  "freeplay_submission": "beta:v80",
  "key_fix": "Extractor memory 600→800 steps. Cumulative +37.9% vs baseline.",
  "approach_stats": {
    "pco": {"attempts": 4, "improvements": 1, "last_used": "20260329-000000"},
    "design": {"attempts": 22, "improvements": 14, "last_used": "20260401-020000"}
  },
  "freeplay_experiments": {
    "v76_hub_hotspot_discount": {"score": "pending", "result": "pending"},
    "v80_extractor_mem_800": {"score": "pending", "result": "pending"},
    "best_v15": {"score": 1.81, "result": "baseline_best"}
  }
}
